ShoubashouDaiNiGodotYouxiKaifaDiyiDanLingJichuRumenAnliFlappybird/README.md
ShoubashouDaiNiGodotYouxiKaifaDiyiDanLingJichuRumenAnliFlappybird/__init__.py
ShoubashouDaiNiGodotYouxiKaifaDiyiDanLingJichuRumenAnliFlappybird/__main__.py
ShoubashouDaiNiGodotYouxiKaifaDiyiDanLingJichuRumenAnliFlappybird/file.epub
ShoubashouDaiNiGodotYouxiKaifaDiyiDanLingJichuRumenAnliFlappybird/index.html
ShoubashouDaiNiGodotYouxiKaifaDiyiDanLingJichuRumenAnliFlappybird/css/__init__.py
ShoubashouDaiNiGodotYouxiKaifaDiyiDanLingJichuRumenAnliFlappybird/css/annotations.css
ShoubashouDaiNiGodotYouxiKaifaDiyiDanLingJichuRumenAnliFlappybird/css/main.css
ShoubashouDaiNiGodotYouxiKaifaDiyiDanLingJichuRumenAnliFlappybird/css/normalize.css
ShoubashouDaiNiGodotYouxiKaifaDiyiDanLingJichuRumenAnliFlappybird/css/popup.css
ShoubashouDaiNiGodotYouxiKaifaDiyiDanLingJichuRumenAnliFlappybird/font/__init__.py
ShoubashouDaiNiGodotYouxiKaifaDiyiDanLingJichuRumenAnliFlappybird/font/fontello.eot
ShoubashouDaiNiGodotYouxiKaifaDiyiDanLingJichuRumenAnliFlappybird/font/fontello.svg
ShoubashouDaiNiGodotYouxiKaifaDiyiDanLingJichuRumenAnliFlappybird/font/fontello.ttf
ShoubashouDaiNiGodotYouxiKaifaDiyiDanLingJichuRumenAnliFlappybird/font/fontello.woff
ShoubashouDaiNiGodotYouxiKaifaDiyiDanLingJichuRumenAnliFlappybird/img/__init__.py
ShoubashouDaiNiGodotYouxiKaifaDiyiDanLingJichuRumenAnliFlappybird/img/annotator-glyph-sprite.png
ShoubashouDaiNiGodotYouxiKaifaDiyiDanLingJichuRumenAnliFlappybird/img/annotator-icon-sprite.png
ShoubashouDaiNiGodotYouxiKaifaDiyiDanLingJichuRumenAnliFlappybird/img/apple-touch-icon.png
ShoubashouDaiNiGodotYouxiKaifaDiyiDanLingJichuRumenAnliFlappybird/img/cancelfullscreen.png
ShoubashouDaiNiGodotYouxiKaifaDiyiDanLingJichuRumenAnliFlappybird/img/close.png
ShoubashouDaiNiGodotYouxiKaifaDiyiDanLingJichuRumenAnliFlappybird/img/fullscreen.png
ShoubashouDaiNiGodotYouxiKaifaDiyiDanLingJichuRumenAnliFlappybird/img/loader.gif
shoubashou_dai_ni_godot_youxi_kaifa_diyi_dan_ling_jichu_rumen_anli_flappybird-2024.3.5.0.dist-info/METADATA
shoubashou_dai_ni_godot_youxi_kaifa_diyi_dan_ling_jichu_rumen_anli_flappybird-2024.3.5.0.dist-info/WHEEL
shoubashou_dai_ni_godot_youxi_kaifa_diyi_dan_ling_jichu_rumen_anli_flappybird-2024.3.5.0.dist-info/entry_points.txt
shoubashou_dai_ni_godot_youxi_kaifa_diyi_dan_ling_jichu_rumen_anli_flappybird-2024.3.5.0.dist-info/top_level.txt
shoubashou_dai_ni_godot_youxi_kaifa_diyi_dan_ling_jichu_rumen_anli_flappybird-2024.3.5.0.dist-info/RECORD
